handle_igblastn/__init__.py
handle_igblastn/_clines.py
handle_igblastn-0.1.0.dist-info/LICENSE.txt
handle_igblastn-0.1.0.dist-info/METADATA
handle_igblastn-0.1.0.dist-info/WHEEL
handle_igblastn-0.1.0.dist-info/top_level.txt
handle_igblastn-0.1.0.dist-info/RECORD
