Metadata-Version: 2.1
Name: handle_igblastn
Version: 0.1.0
Summary: Handle igblastn.
Author-email: Johannes Programming <johannes-programming@posteo.org>
License: The MIT License (MIT)
Project-URL: Download, https://pypi.org/project/handle-igblastn/#files
Project-URL: Source, https://github.com/johannes-programming/handle_igblastn
Classifier: License :: OSI Approved :: MIT License
Classifier: Programming Language :: Python
Classifier: Programming Language :: Python :: 3
Requires-Python: >=3.11
License-File: LICENSE.txt
